cigam.py
cigam-0.0.2.dist-info/DESCRIPTION.rst
cigam-0.0.2.dist-info/METADATA
cigam-0.0.2.dist-info/RECORD
cigam-0.0.2.dist-info/WHEEL
cigam-0.0.2.dist-info/metadata.json
cigam-0.0.2.dist-info/top_level.txt
